0 DEF fact_iter
1 PUSH_LOCAL_I n
2 PUSH_LOCAL_I resultado
3 PUSH_LOCAL_I i
4 LOAD_CONST 1
5 STORE_FAST resultado
6 LOAD_CONST 1
7 STORE_FAST i
8 LOAD_FAST i
9 LOAD_FAST n
10 COMPARE_OP <=
11 JUMP_IF_FALSE 21
12 LOAD_FAST resultado
13 LOAD_FAST i
14 BINARY_MULTIPLY
15 STORE_FAST resultado
16 LOAD_FAST i
17 LOAD_CONST 1
18 BINARY_ADD
19 STORE_FAST i
20 JUMP_ABSOLUTE 8
21 LOAD_FAST resultado
22 RETURN_VALUE
23 DEF Main
24 LOAD_CONST 'F'
25 LOAD_GLOBAL write
26 CALL_FUNCTION 0
27 LOAD_CONST 'F'
28 LOAD_CONST 5
29 LOAD_GLOBAL  fact_iter()
30 CALL_FUNCTION 1
31 LOAD_GLOBAL write
32 CALL_FUNCTION 1
33 LOAD_CONST 5
34 LOAD_GLOBAL  fact_iter()
35 CALL_FUNCTION 1
36 END  
