0 PUSH_GLOBAL_I n
1 PUSH_GLOBAL_C res
2 LOAD_GLOBAL  calcularFac()
3 STORE_FAST 0
4 LOAD_GLOBAL num
6 COMPARE_OP <=
7 STORE_FAST 1
8 STORE_FAST 1
9 LOAD_GLOBAL num
10 BINARY_MULTIPLY
11 LOAD_GLOBAL calcularFac(num-1)
12 LOAD_GLOBAL num
13 BINARY_SUBSTRACT
14 STORE_FAST 1
15 CALL_FUNCTION 1
15 STORE_FAST calcularFac(num-1)
16 STORE_FAST (calcularFac(num-1))
17 BINARY_MULTIPLY
18 LOAD_GLOBAL num_aux
19 LOAD_FAST  num_aux
20 RETURN_VALUE
21 LOAD_GLOBAL  Main()
22 STORE_FAST 5
23 LOAD_GLOBAL n
24 CALL_FUNCTION 1
24 STORE_FAST calcularFac(n)
25 STORE_FAST 'F'
26 LOAD_GLOBAL res
27 STORE_FAST ':'
28 STORE_FAST 'a'
29 LOAD_GLOBAL n
30 RETURN
31 END  
